README
setup.py
MercurialRecipe.egg-info/PKG-INFO
MercurialRecipe.egg-info/SOURCES.txt
MercurialRecipe.egg-info/dependency_links.txt
MercurialRecipe.egg-info/entry_points.txt
MercurialRecipe.egg-info/requires.txt
MercurialRecipe.egg-info/top_level.txt
MercurialRecipe.egg-info/zip-safe
mercurialrecipe/__init__.py