Metadata-Version: 1.0
Name: MercurialRecipe
Version: 0.1
Summary: zc.buildout recipe for cloning Mercurial repository
Home-page: http://bitbucket.org/tawm/mercurial-recipe/
Author: Tim Molendijk
Author-email: tim@timmolendijk.nl
License: UNKNOWN
Platform: UNKNOWN
Classifier: Development Status :: 3 - Alpha
Classifier: Environment :: Plugins
Classifier: Framework :: Buildout
Classifier: Intended Audience :: Developers
Classifier: Intended Audience :: System Administrators
Classifier: License :: OSI Approved
Classifier: Natural Language :: English
Classifier: Programming Language :: Python
Classifier: Topic :: Software Development :: Version Control
